coarnotify/__init__.py
coarnotify/client.py
coarnotify/exceptions.py
coarnotify/factory.py
coarnotify/http.py
coarnotify/server.py
coarnotify/validate.py
coarnotify/core/__init__.py
coarnotify/core/activitystreams2.py
coarnotify/core/notify.py
coarnotify/patterns/__init__.py
coarnotify/patterns/accept.py
coarnotify/patterns/announce_endorsement.py
coarnotify/patterns/announce_relationship.py
coarnotify/patterns/announce_review.py
coarnotify/patterns/announce_service_result.py
coarnotify/patterns/reject.py
coarnotify/patterns/request_endorsement.py
coarnotify/patterns/request_review.py
coarnotify/patterns/tentatively_accept.py
coarnotify/patterns/tentatively_reject.py
coarnotify/patterns/undo_offer.py
coarnotify/patterns/unprocessable_notification.py
coarnotify/test/__init__.py
coarnotify/test/fixtures/__init__.py
coarnotify/test/fixtures/accept.py
coarnotify/test/fixtures/announce_endorsement.py
coarnotify/test/fixtures/announce_relationship.py
coarnotify/test/fixtures/announce_review.py
coarnotify/test/fixtures/announce_service_result.py
coarnotify/test/fixtures/base_fixture_factory.py
coarnotify/test/fixtures/notify.py
coarnotify/test/fixtures/reject.py
coarnotify/test/fixtures/request_endorsement.py
coarnotify/test/fixtures/request_review.py
coarnotify/test/fixtures/tentatively_accept.py
coarnotify/test/fixtures/tentatively_reject.py
coarnotify/test/fixtures/undo_offer.py
coarnotify/test/fixtures/unprocessable_notification.py
coarnotify/test/fixtures/uris.py
coarnotify/test/integration/__init__.py
coarnotify/test/integration/test_client.py
coarnotify/test/mocks/__init__.py
coarnotify/test/mocks/http.py
coarnotify/test/server/__init__.py
coarnotify/test/server/inbox.py
coarnotify/test/server/settings.py
coarnotify/test/unit/__init__.py
coarnotify/test/unit/test_activitystreams.py
coarnotify/test/unit/test_client.py
coarnotify/test/unit/test_factory.py
coarnotify/test/unit/test_models.py
coarnotify/test/unit/test_validate.py
coarnotify-1.0.1.3.dist-info/LICENCE
coarnotify-1.0.1.3.dist-info/METADATA
coarnotify-1.0.1.3.dist-info/WHEEL
coarnotify-1.0.1.3.dist-info/top_level.txt
coarnotify-1.0.1.3.dist-info/RECORD
