Metadata-Version: 2.2
Name: coarnotify
Version: 1.0.1.3
Summary: COAR Notify Common Library
Author: Cottage Labs
Author-email: richard@cottagelabs.com
License: Apache2
License-File: LICENCE
Requires-Dist: requests
Provides-Extra: docs
Requires-Dist: sphinx; extra == "docs"
Requires-Dist: sphinx-autoapi; extra == "docs"
Provides-Extra: test
Requires-Dist: Flask>3.0.0; extra == "test"
Dynamic: author
Dynamic: author-email
Dynamic: description
Dynamic: description-content-type
Dynamic: license
Dynamic: provides-extra
Dynamic: requires-dist
Dynamic: summary
